nat/meta/pypi.md
nat/plugins/redis/__init__.py
nat/plugins/redis/memory.py
nat/plugins/redis/object_store.py
nat/plugins/redis/redis_editor.py
nat/plugins/redis/redis_object_store.py
nat/plugins/redis/register.py
nat/plugins/redis/schema.py
nvidia_nat_redis-1.3.1.dist-info/licenses/LICENSE-3rd-party.txt
nvidia_nat_redis-1.3.1.dist-info/licenses/LICENSE.md
nvidia_nat_redis-1.3.1.dist-info/METADATA
nvidia_nat_redis-1.3.1.dist-info/WHEEL
nvidia_nat_redis-1.3.1.dist-info/entry_points.txt
nvidia_nat_redis-1.3.1.dist-info/top_level.txt
nvidia_nat_redis-1.3.1.dist-info/RECORD
